eventb_to_txt/__init__.py
eventb_to_txt/__main__.py
eventb_to_txt/abstract.py
eventb_to_txt/context.py
eventb_to_txt/machine.py
eventb_to_txt/model.py
eventb_to_txt-1.6.dist-info/LICENSE
eventb_to_txt-1.6.dist-info/METADATA
eventb_to_txt-1.6.dist-info/WHEEL
eventb_to_txt-1.6.dist-info/entry_points.txt
eventb_to_txt-1.6.dist-info/top_level.txt
eventb_to_txt-1.6.dist-info/RECORD
