Metadata-Version: 2.1
Name: eventb-to-txt
Version: 1.6
Summary: Event-B to txt converter
Home-page: https://github.com/17451k/eventb-to-txt
Author: Ilya Shchepetkov
Author-email: ilya.shchepetkov@gmail.com
License: LICENSE.txt
Classifier: Programming Language :: Python :: 3
Classifier: Programming Language :: Python :: 3.7
Classifier: Programming Language :: Python :: 3.8
Classifier: Programming Language :: Python :: 3.9
Classifier: Programming Language :: Python :: 3.10
Classifier: Programming Language :: Python :: 3.11
Classifier: Programming Language :: Python :: Implementation :: CPython
Classifier: License :: OSI Approved :: MIT License
Classifier: Operating System :: Unix
Classifier: Operating System :: MacOS :: MacOS X
Requires-Python: >=3.7
License-File: LICENSE
